{
  "main": {
    "id": "b0047ebc5a6266d6",
    "type": "split",
    "children": [
      {
        "id": "30c607474e0f2ed0",
        "type": "tabs",
        "children": [
          {
            "id": "64ff80b1966807b5",
            "type": "leaf",
            "pinned": true,
            "state": {
              "type": "pdf",
              "state": {
                "file": "Sources/Introduction_To_Automata_Theory-John_Hopcroft.pdf"
              },
              "pinned": true,
              "icon": "lucide-file-text",
              "title": "Introduction_To_Automata_Theory-John_Hopcroft"
            }
          },
          {
            "id": "393daa9274d1a051",
            "type": "leaf",
            "state": {
              "type": "split-diff-view",
              "state": {
                "aFile": "Questions/Bachelor's Questions/24. Numerické metody.md",
                "bFile": "Questions/Bachelor's Questions/24. Numerické metody.md",
                "aRef": "HEAD",
                "bRef": ""
              },
              "icon": "diff",
              "title": "Diff: 24. Numerické metody"
            }
          }
        ],
        "currentTab": 1
      }
    ],
    "direction": "vertical"
  },
  "left": {
    "id": "f1fd233d6b8fa84b",
    "type": "split",
    "children": [
      {
        "id": "b3843c24be7ac5d7",
        "type": "tabs",
        "children": [
          {
            "id": "190e1811de4ec1a4",
            "type": "leaf",
            "state": {
              "type": "file-explorer",
              "state": {
                "sortOrder": "alphabetical",
                "autoReveal": false
              },
              "icon": "lucide-folder-closed",
              "title": "Files"
            }
          },
          {
            "id": "c54f0659360ad1a8",
            "type": "leaf",
            "state": {
              "type": "search",
              "state": {
                "query": "set",
                "matchingCase": false,
                "explainSearch": false,
                "collapseAll": false,
                "extraContext": false,
                "sortOrder": "alphabetical"
              },
              "icon": "lucide-search",
              "title": "Search"
            }
          },
          {
            "id": "229735d3a0129dfa",
            "type": "leaf",
            "state": {
              "type": "bookmarks",
              "state": {},
              "icon": "lucide-bookmark",
              "title": "Bookmarks"
            }
          }
        ]
      }
    ],
    "direction": "horizontal",
    "width": 363.5
  },
  "right": {
    "id": "232ea24c7b8ecb6d",
    "type": "split",
    "children": [
      {
        "id": "efc942edd69ce9e8",
        "type": "tabs",
        "children": [
          {
            "id": "a01fddf47a9b6567",
            "type": "leaf",
            "state": {
              "type": "backlink",
              "state": {
                "file": "Sources/Introduction_To_Automata_Theory-John_Hopcroft.pdf",
                "collapseAll": true,
                "extraContext": false,
                "sortOrder": "alphabetical",
                "showSearch": false,
                "searchQuery": "",
                "backlinkCollapsed": false,
                "unlinkedCollapsed": false
              },
              "icon": "links-coming-in",
              "title": "Backlinks for Introduction_To_Automata_Theory-John_Hopcroft"
            }
          },
          {
            "id": "be3464cf8a01dcbf",
            "type": "leaf",
            "state": {
              "type": "outgoing-link",
              "state": {
                "linksCollapsed": false,
                "unlinkedCollapsed": true
              },
              "icon": "links-going-out",
              "title": "Outgoing links"
            }
          },
          {
            "id": "ec9001eed99b9997",
            "type": "leaf",
            "state": {
              "type": "tag",
              "state": {
                "sortOrder": "frequency",
                "useHierarchy": true,
                "showSearch": false,
                "searchQuery": ""
              },
              "icon": "lucide-tags",
              "title": "Tags"
            }
          },
          {
            "id": "92ffa216844ab14e",
            "type": "leaf",
            "state": {
              "type": "outline",
              "state": {
                "followCursor": false,
                "showSearch": false,
                "searchQuery": ""
              },
              "icon": "lucide-list",
              "title": "Outline"
            }
          },
          {
            "id": "f15a05c96728846f",
            "type": "leaf",
            "state": {
              "type": "git-view",
              "state": {},
              "icon": "git-pull-request",
              "title": "Source Control"
            }
          }
        ],
        "currentTab": 4
      }
    ],
    "direction": "horizontal",
    "width": 853.5
  },
  "left-ribbon": {
    "hiddenItems": {
      "switcher:Open quick switcher": false,
      "graph:Open graph view": false,
      "canvas:Create new canvas": false,
      "daily-notes:Open today's daily note": false,
      "templates:Insert template": false,
      "command-palette:Open command palette": false,
      "obsidian-excalidraw-plugin:New drawing": false,
      "obsidian-git:Open Git source control": false
    }
  },
  "active": "393daa9274d1a051",
  "lastOpenFiles": [
    "Study Materials/Math/Linear Algebra/Matrix.md",
    "Study Materials/Automata/Types/Stack Automata.md",
    "Study Materials/Math/Logic/Propositional Logic.md",
    "Study Materials/Math/Logic/Predicate Logic.md",
    "Questions/Bachelor's Questions/19. Výroková logika a predikátová logika.md",
    "Sources/Introduction_To_Automata_Theory-John_Hopcroft.pdf",
    "Excalidraw/Automata/Automata_Diagram.md",
    "Excalidraw/Automata/Stack_Automata_Diagram.md",
    "Excalidraw/Automata/Mealy_Automata.md",
    "Study Materials/Automata/Types/Finite Automata.md",
    "Study Materials/Automata/Types/Automata.md",
    "Study Materials/Automata/Automata Theory.md",
    "Study Materials/Automata/Terms/Language.md",
    "Questions/Bachelor's Questions/3. Sekvenční logické obvody.md",
    "Study Materials/Math/Proof/Formal Proof.md",
    "README.md",
    "Study Materials/Automata/Chomsky Hierarchy.md",
    "Untitled.md",
    "bibtext_book_template.md",
    "Study Materials/Automata/Languages/Regular/Regular Language.md",
    "Study Materials/Automata/Terms/String.md",
    "Study Materials/Automata/Terms/Alphabet.md",
    "Study Materials/Automata/Languages/Regular/Pumping Lemma.md",
    "Study Materials/Automata/Languages/Regular/Regular Expressions.md",
    "Study Materials/Automata/Languages/Regular/Regular Grammar.md",
    "Study Materials/Automata/Languages/Context-Free/Context-Free Grammar.md",
    "Study Materials/Automata/Languages/Context-Free/Context-Free Language.md",
    "Study Materials/Automata/Terms",
    "Study Materials/Automata/Languages/Context-Free",
    "Study Materials/Automata/Languages",
    "Study Materials/Automata/Languages/Regular",
    "Study Materials/Math/Proofs/Untitled",
    "Study Materials/Math/Proof",
    "Study Materials/Diagrams",
    "Sources/SZZ_okruhy_all.pdf",
    "Sources/Introduction To Automata Theory_john hopcroft.pdf",
    "Study Materials/Processing/Untitled.canvas",
    "Untitled.canvas"
  ]
}